Metadata-Version: 2.1
Name: tellolib
Version: 1.0.1
Summary: A library meant to fly the tello drone
Author: Aarav Prakash
